vsss_client/__init__.py
vsss_client/command_pb2.py
vsss_client/common_pb2.py
vsss_client/packet_pb2.py
vsss_client/replacement_pb2.py
vsss_client-0.1.3.dist-info/LICENSE
vsss_client-0.1.3.dist-info/METADATA
vsss_client-0.1.3.dist-info/WHEEL
vsss_client-0.1.3.dist-info/top_level.txt
vsss_client-0.1.3.dist-info/RECORD
